{
    "type": "carousel",
    "contents": [
        {
            "type": "bubble",
            "hero": {
                "type": "box",
                "layout": "vertical",
                "contents": [
                    {
                        "type": "button",
                        "action": {
                            "type": "message",
                            "label": "test",
                            "text": "hello"
                        }
                    }
                ]
            }
        },
        {
            "type": "bubble",
            "body": {
                "type": "box",
                "layout": "vertical",
                "contents": [
                    {
                        "type": "button",
                        "action": {
                            "type": "uri",
                            "label": "action",
                            "uri": "http://linecorp.com/"
                        }
                    }
                ]
            }
        }
    ]
}